Metadata-Version: 2.1
Name: jkh011120-algolib
Version: 0.0.1
Summary: nice algolib
Home-page: http://github.io/jkh011120/algolib
Download-URL: http://github.com/jkh011120/algolib/mm.zip
Author: jkh011120
License: UNKNOWN
Platform: UNKNOWN
Classifier: Programming Language :: Python :: 3
